Tensorblow/D1.py
Tensorblow/D3.py
Tensorblow/D4.py
Tensorblow/D5.py
Tensorblow/D7.py
Tensorblow/D8.py
Tensorblow/M1.py
Tensorblow/M2.py
Tensorblow/M3.py
Tensorblow/M6.py
Tensorblow/M7.py
Tensorblow/M8.py
Tensorblow/__init__.py
tensorblow-2.17.0.dist-info/licenses/LICENCE.txt
tensorblow-2.17.0.dist-info/METADATA
tensorblow-2.17.0.dist-info/WHEEL
tensorblow-2.17.0.dist-info/top_level.txt
tensorblow-2.17.0.dist-info/RECORD
